VuVoPy/__init__.py
VuVoPy/data/__init__.py
VuVoPy/data/containers/__init__.py
VuVoPy/data/containers/prepocessing.py
VuVoPy/data/containers/sample.py
VuVoPy/data/containers/segmentation.py
VuVoPy/data/containers/test_voicedsample.py
VuVoPy/data/containers/voiced_sample.py
VuVoPy/data/utils/__init__.py
VuVoPy/data/utils/formant_frequencies.py
VuVoPy/data/utils/fundamental_frequency.py
VuVoPy/data/utils/swipep.py
VuVoPy/data/utils/vuvs_detection.py
VuVoPy/data/utils/vuvs_gmm.py
VuVoPy/features/__init__.py
VuVoPy/features/utils/__init__.py
VuVoPy/features/utils/durmad.py
VuVoPy/features/utils/durmed.py
VuVoPy/features/utils/duv.py
VuVoPy/features/utils/hnr.py
VuVoPy/features/utils/hnr_cepstral.py
VuVoPy/features/utils/hnr_fft.py
VuVoPy/features/utils/hnr_swipe.py
VuVoPy/features/utils/jitter.py
VuVoPy/features/utils/mpt.py
VuVoPy/features/utils/ppr.py
VuVoPy/features/utils/relf0sd.py
VuVoPy/features/utils/relf1f2sd.py
VuVoPy/features/utils/relseosd.py
VuVoPy/features/utils/shimmer.py
VuVoPy/features/utils/spir.py
vuvopy-1.0.0.dist-info/licenses/LICENSE.txt
vuvopy-1.0.0.dist-info/METADATA
vuvopy-1.0.0.dist-info/WHEEL
vuvopy-1.0.0.dist-info/top_level.txt
vuvopy-1.0.0.dist-info/RECORD
