Metadata-Version: 2.4
Name: VuVoPy
Version: 1.0.0
Summary: Voice features
Author-email: Richard Ladislav <230106@vut.cz>
License: MIT
Project-URL: Homepage, https://github.com/RichardLadislav/VuVoPy
Keywords: voice,features,speech,parkinson,acoustic-analysis
Classifier: License :: OSI Approved :: MIT License
Classifier: Programming Language :: Python
Classifier: Programming Language :: Python :: 3.7
Classifier: Programming Language :: Python :: 3.8
Classifier: Programming Language :: Python :: 3.9
Classifier: Programming Language :: Python :: 3.10
Classifier: Programming Language :: Python :: Implementation :: PyPy
Classifier: Operating System :: OS Independent
Requires-Python: >=3.7
License-File: LICENSE.txt
Requires-Dist: numpy
Requires-Dist: pandas
Requires-Dist: scipy
Requires-Dist: librosa
Requires-Dist: matplotlib
Requires-Dist: scikit-learn
Requires-Dist: sympy
Requires-Dist: sphinx
Requires-Dist: sphinx_rtd_theme
Dynamic: license-file
